odoo/addons/pos_ticket_extra_company_info_l10n_fr/README.rst
odoo/addons/pos_ticket_extra_company_info_l10n_fr/__init__.py
odoo/addons/pos_ticket_extra_company_info_l10n_fr/__manifest__.py
odoo/addons/pos_ticket_extra_company_info_l10n_fr/i18n/fr.po
odoo/addons/pos_ticket_extra_company_info_l10n_fr/i18n/it.po
odoo/addons/pos_ticket_extra_company_info_l10n_fr/i18n/pos_ticket_extra_company_info_l10n_fr.pot
odoo/addons/pos_ticket_extra_company_info_l10n_fr/models/__init__.py
odoo/addons/pos_ticket_extra_company_info_l10n_fr/models/pos_session.py
odoo/addons/pos_ticket_extra_company_info_l10n_fr/readme/CONTRIBUTORS.rst
odoo/addons/pos_ticket_extra_company_info_l10n_fr/readme/CREDITS.rst
odoo/addons/pos_ticket_extra_company_info_l10n_fr/readme/DESCRIPTION.rst
odoo/addons/pos_ticket_extra_company_info_l10n_fr/static/description/icon.png
odoo/addons/pos_ticket_extra_company_info_l10n_fr/static/description/index.html
odoo/addons/pos_ticket_extra_company_info_l10n_fr/static/description/pos_ticket.png
odoo/addons/pos_ticket_extra_company_info_l10n_fr/static/src/js/models.esm.js
odoo/addons/pos_ticket_extra_company_info_l10n_fr/static/src/xml/OrderReceipt.xml
odoo/addons/pos_ticket_extra_company_info_l10n_fr/views/templates.xml
odoo_addon_pos_ticket_extra_company_info_l10n_fr-16.0.1.0.0.4.dist-info/METADATA
odoo_addon_pos_ticket_extra_company_info_l10n_fr-16.0.1.0.0.4.dist-info/WHEEL
odoo_addon_pos_ticket_extra_company_info_l10n_fr-16.0.1.0.0.4.dist-info/top_level.txt
odoo_addon_pos_ticket_extra_company_info_l10n_fr-16.0.1.0.0.4.dist-info/RECORD
